realm_keeper/__init__.py
realm_keeper/models/__init__.py
realm_keeper/models/game_manager.py
realm_keeper/models/game_object.py
realm_keeper/models/game_repository.py
realm_keeper/models/game_session_manager.py
realm_keeper/models/game_world.py
realm_keeper/repositories/__init__.py
realm_keeper/repositories/memory_game_repository.py
game_realm_keeper-0.4.0.dist-info/METADATA
game_realm_keeper-0.4.0.dist-info/WHEEL
game_realm_keeper-0.4.0.dist-info/RECORD
