Metadata-Version: 2.1
Name: game-realm-keeper
Version: 0.4.0
Summary: A package to manage RPG resources.
Author: sebastian-hsu
Author-email: sebastian.hsu@gmail.com
Requires-Python: >=3.11,<4.0
Classifier: Programming Language :: Python :: 3
Classifier: Programming Language :: Python :: 3.11
Classifier: Programming Language :: Python :: 3.12
Requires-Dist: build (>=1.2.1,<2.0.0)
Requires-Dist: pydantic (>=2.8.2,<3.0.0)
Requires-Dist: twine (>=5.1.1,<6.0.0)
